markdown2slack/.coverage
markdown2slack/__init__.py
markdown2slack/app.py
markdown2slack-0.2.0.dist-info/LICENSE
markdown2slack-0.2.0.dist-info/METADATA
markdown2slack-0.2.0.dist-info/WHEEL
markdown2slack-0.2.0.dist-info/RECORD
