Metadata-Version: 2.1
Name: markdown2slack
Version: 0.2.0
Summary: markdown2slack is converter markdown to slack format
License: Beerware
Author: Rodrigo da Silva Rios
Author-email: rodrigosr.rios@live.com
Requires-Python: >=3.11,<4.0
Classifier: License :: Other/Proprietary License
Classifier: Programming Language :: Python :: 3
Classifier: Programming Language :: Python :: 3.11
Project-URL: Source, https://github.com/Rodrigo-Rios/Markdown2Slack
